yta_validation/__init__.py
yta_validation/error_message.py
yta_validation/number.py
yta_validation/parameter.py
yta_validation-0.0.36.dist-info/licenses/LICENSE
yta_validation-0.0.36.dist-info/METADATA
yta_validation-0.0.36.dist-info/WHEEL
yta_validation-0.0.36.dist-info/RECORD
