Metadata-Version: 2.4
Name: yta-validation
Version: 0.0.36
Summary: Youtube Autonomous Validation Module
License-File: LICENSE
Author: danialcala94
Author-email: danielalcalavalera@gmail.com
Requires-Python: ==3.9
Classifier: Programming Language :: Python :: 3
Classifier: Programming Language :: Python :: 3.9
Requires-Dist: validators (>=0.34.0,<9.0.0)
